LICENSE.md
MANIFEST.in
README.md
requirements.txt
setup.py
wormhole/__init__.py
wormhole/controller.py
wormhole/core.py
wormhole/utils.py
wormhole/version.py
wormhole/assets/logo.png
wormhole/assets/logo.svg
wormhole/assets/logo_white.png
wormhole/assets/logo_white.svg
wormhole/assets/poweredby.png
wormhole/assets/poweredby.svg
wormhole/assets/poweredby_white.png
wormhole/assets/poweredby_white.svg
wormhole/streamer/__init__.py
wormhole/streamer/abstractstreamer.py
wormhole/streamer/mjpegstreamer.py
wormhole/streamer/rawstreamer.py
wormhole/streamer/socketiostreamer.py
wormhole/video/__init__.py
wormhole/video/abstractvideo.py
wormhole/video/cameravideo.py
wormhole/video/customvideo.py
wormhole/video/filevideo.py
wormhole/video/imagevideo.py
wormhole/video/videocopy.py
wormhole/video/videorender.py
wormhole/video/videowriter.py
wormhole/viewer/__init__.py
wormhole/viewer/abstractviewer.py
wormhole/viewer/mjpegviewer.py
wormhole/viewer/rawviewer.py
wormhole/viewer/socketioviewer.py
wormhole_streaming.egg-info/PKG-INFO
wormhole_streaming.egg-info/SOURCES.txt
wormhole_streaming.egg-info/dependency_links.txt
wormhole_streaming.egg-info/requires.txt
wormhole_streaming.egg-info/top_level.txt