Metadata-Version: 2.1
Name: wormhole-streaming
Version: 1.0.0
Summary: Simple and Hackable Realtime Video Streaming Engine
Home-page: https://github.com/RadioactiveHydra/Wormhole/
Author: Edward Li
Project-URL: Source Code, https://github.com/RadioactiveHydra/Wormhole
Project-URL: Bug Reports, https://github.com/RadioactiveHydra/Wormhole/issues
Project-URL: Demo, https://demo.wormhole.hydranet.dev/
Project-URL: Discord, https://discord.gg/9QF2bPc
Requires-Python: >=3.9
License-File: LICENSE.md
